odoo/addons/ssi_financial_accounting/README.rst
odoo/addons/ssi_financial_accounting/__init__.py
odoo/addons/ssi_financial_accounting/__manifest__.py
odoo/addons/ssi_financial_accounting/menu.xml
odoo/addons/ssi_financial_accounting/data/account_journal_data.xml
odoo/addons/ssi_financial_accounting/data/account_type_data.xml
odoo/addons/ssi_financial_accounting/data/ir_sequence_data.xml
odoo/addons/ssi_financial_accounting/data/sequence_template_data.xml
odoo/addons/ssi_financial_accounting/data/policy/account_bank_statement/policy_template_data.xml
odoo/addons/ssi_financial_accounting/data/policy/account_move/customer_cn_policy_template_data.xml
odoo/addons/ssi_financial_accounting/data/policy/account_move/customer_invoice_policy_template_data.xml
odoo/addons/ssi_financial_accounting/data/policy/account_move/entry_policy_template_data.xml
odoo/addons/ssi_financial_accounting/data/policy/account_move/purchase_receipt_policy_template_data.xml
odoo/addons/ssi_financial_accounting/data/policy/account_move/sale_receipt_policy_template_data.xml
odoo/addons/ssi_financial_accounting/data/policy/account_move/vendor_bill_policy_template_data.xml
odoo/addons/ssi_financial_accounting/data/policy/account_move/vendor_cn_policy_template_data.xml
odoo/addons/ssi_financial_accounting/data/policy/account_payment/customer_receipt.xml
odoo/addons/ssi_financial_accounting/data/policy/account_payment/vendor_payment.xml
odoo/addons/ssi_financial_accounting/models/__init__.py
odoo/addons/ssi_financial_accounting/models/account_account.py
odoo/addons/ssi_financial_accounting/models/account_bank_statement.py
odoo/addons/ssi_financial_accounting/models/account_move.py
odoo/addons/ssi_financial_accounting/models/account_move_line.py
odoo/addons/ssi_financial_accounting/models/account_payment.py
odoo/addons/ssi_financial_accounting/models/account_type.py
odoo/addons/ssi_financial_accounting/models/cash_flow_type.py
odoo/addons/ssi_financial_accounting/models/mis_report_instance.py
odoo14_addon_ssi_financial_accounting-14.0.7.1.0.dist-info/METADATA
odoo14_addon_ssi_financial_accounting-14.0.7.1.0.dist-info/WHEEL
odoo14_addon_ssi_financial_accounting-14.0.7.1.0.dist-info/top_level.txt
odoo14_addon_ssi_financial_accounting-14.0.7.1.0.dist-info/RECORD
