Metadata-Version: 2.1
Name: odoo14-addon-ssi_financial_accounting
Version: 14.0.7.1.0
Summary: Financial Accounting
Home-page: https://simetri-sinergi.id
Author: OpenSynergy Indonesia, PT. Simetri Sinergi Indonesia
License: AGPL-3
Classifier: Programming Language :: Python
Classifier: Framework :: Odoo
Classifier: Framework :: Odoo :: 14.0
Classifier: License :: OSI Approved :: GNU Affero General Public License v3
Requires-Python: >=3.6
Requires-Dist: odoo14-addon-account-financial-report
Requires-Dist: odoo14-addon-account-invoice-force-number
Requires-Dist: odoo14-addon-account-journal-lock-date
Requires-Dist: odoo14-addon-account-move-force-removal
Requires-Dist: odoo14-addon-account-reconciliation-widget
Requires-Dist: odoo14-addon-account-statement-import-txt-xlsx
Requires-Dist: odoo14-addon-configuration-helper
Requires-Dist: odoo14-addon-currency-rate-inverted
Requires-Dist: odoo14-addon-mis-builder
Requires-Dist: odoo14-addon-mis-template-financial-report
Requires-Dist: odoo14-addon-ssi-master-data-mixin
Requires-Dist: odoo14-addon-ssi-policy-mixin
Requires-Dist: odoo14-addon-ssi-print-mixin
Requires-Dist: odoo14-addon-ssi-sequence-mixin
Requires-Dist: odoo<14.1dev,>=14.0a
